iree_tools_xla-20230404.479.dist-info/METADATA
iree_tools_xla-20230404.479.dist-info/entry_points.txt
iree_tools_xla-20230404.479.dist-info/RECORD
iree_tools_xla-20230404.479.dist-info/top_level.txt
iree_tools_xla-20230404.479.dist-info/WHEEL
iree/tools/xla/__init__.py
iree/tools/xla/iree-import-xla
iree/tools/xla/scripts/iree_import_xla/__main__.py
