Metadata-Version: 2.1
Name: iree-tools-xla
Version: 20230404.479
Summary: IREE XLA Compiler Tools
Home-page: https://github.com/openxla/iree
Author: The IREE Team
Author-email: iree-discuss@googlegroups.com
License: Apache-2.0
Classifier: Development Status :: 3 - Alpha
Classifier: License :: OSI Approved :: Apache Software License
Classifier: Programming Language :: Python :: 3
Classifier: Programming Language :: Python :: 3.8
Classifier: Programming Language :: Python :: 3.9
Classifier: Programming Language :: Python :: 3.10
Requires-Python: >=3.8
